{"adult & obscenity": ["n\u1ee9ng", "kh\u1ecfa th\u00e2n", "l\u1ed9 clip", "sex", "th\u1ee7 d\u00e2m", "t\u00e0 d\u00e2m", "d\u00e2m d\u1ee5c", "sexy", "th\u1ee7 d\u00e2m", "v\u00fa to", "\u0111\u00edt", "v\u00fa tr\u00f2n"], "arms": [], "crime": ["ch\u1ebft", "t\u1eed vong", "gi\u1ebft", "hi\u1ebfp d\u00e2m", "\u0111\u1ed5 m\u00e1u", "s\u00e1t h\u1ea1i", "\u0111\u00e2m ch\u1ebft"], "death_injury": ["ch\u1ebft", "t\u1eed vong", "gi\u1ebft", "hi\u1ebfp d\u00e2m", "\u0111\u1ed5 m\u00e1u", "s\u00e1t h\u1ea1i", "\u0111\u00e2m ch\u1ebft"], "download": [], "drugs": [], "hatespeech": ["n\u1ee9ng", "kh\u1ecfa th\u00e2n", "l\u1ed9 clip", "sex", "th\u1ee7 d\u00e2m", "t\u00e0 d\u00e2m", "d\u00e2m d\u1ee5c", "sexy", "th\u1ee7 d\u00e2m", "v\u00fa to", "\u0111\u00edt", "v\u00fa tr\u00f2n", "ch\u1ebft", "t\u1eed vong", "gi\u1ebft", "hi\u1ebfp d\u00e2m", "\u0111\u1ed5 m\u00e1u", "s\u00e1t h\u1ea1i", "\u0111\u00e2m ch\u1ebft", "\u0111\u1ecbt", "\u0111\u1ee5 m\u00e1"], "military": ["ch\u1ebft ", "chi\u1ebfn tranh", "v\u0169 kh\u00ed", "\u0111\u1eabm m\u00e1u", "ng\u1eebng b\u1eafn", "gi\u1ebft", "c\u1ee5t tay", "c\u1ee5t ch\u00e2n", "m\u00f9 m\u1eaft"], "terrorism": [], "tobacco": [], "political": [], "others": [], "game": [], "crypto": [], "wine": ["r\u01b0\u1ee3u ngon", "n\u1ed3ng \u0111\u1ed9 c\u1ed3n", "wine", "r\u01b0\u1ee3u ngo\u1ea1i", "nh\u1eadp kh\u1ea9u", "r\u01b0\u1ee3u n\u1ebfp"], "T\u00e0i ch\u00ednh": [], "Block key": ["Kenh14", "kenh14", "Soha", "soha"]}